gs1grader/__init__.py
gs1grader/common.py
gs1grader/grader_api.py
gs1grader/grader_factory.py
gs1grader/grader_interface.py
gs1grader/graders/__init__.py
gs1grader/graders/axial_non_uniformity_grader.py
gs1grader/graders/fixed_pattern_damage_grader.py
gs1grader/graders/grid_non_uniformity_grader.py
gs1grader/graders/modulation_grader.py
gs1grader/graders/symbol_contrast_grader.py
gs1grader/graders/uec_grader.py
gs1grader/reader/__init__.py
gs1grader/reader/data_matrix_decoder.py
gs1grader/reader/data_matrix_reader.py
gs1grader-1.0.1.dist-info/LICENSE
gs1grader-1.0.1.dist-info/METADATA
gs1grader-1.0.1.dist-info/WHEEL
gs1grader-1.0.1.dist-info/RECORD
