Metadata-Version: 2.3
Name: gs1grader
Version: 1.0.1
Summary: A library for grading Data Matrix codes via GS1 QA metrics
License: AGPL-3.0
Keywords: GS1,Data Matrix,grading,quality assurance
Author: Ceyeb.org
Author-email: info@ceyeb.org
Requires-Python: >=3.9,<3.13
Classifier: Programming Language :: Python :: 3
Classifier: Programming Language :: Python :: 3.9
Classifier: Programming Language :: Python :: 3.10
Classifier: Programming Language :: Python :: 3.11
Classifier: License :: OSI Approved :: GNU Affero General Public License v3
Classifier: Operating System :: OS Independent
Requires-Dist: matplotlib (>=3.8.2,<4.0)
Requires-Dist: numpy (>=1.26,<2.0)
Requires-Dist: opencv-python (>=4.8,<5.0)
Requires-Dist: pylibdmtx-gs1grader (>=0.1.11,<1.0)
Project-URL: Documentation, https://ceyeborg.github.io/GS1Grader
Project-URL: Repository, https://github.com/Ceyeborg/GS1Grader
